catopuma/__init__.py
catopuma/__version__.py
catopuma/prediction_loops.py
catopuma/preprocessing.py
catopuma/uploader.py
catopuma_RiccardoBiondi96-1.0.0.dev1.dist-info/METADATA
catopuma_RiccardoBiondi96-1.0.0.dev1.dist-info/WHEEL
catopuma_RiccardoBiondi96-1.0.0.dev1.dist-info/top_level.txt
catopuma_RiccardoBiondi96-1.0.0.dev1.dist-info/RECORD
