Metadata-Version: 2.1
Name: catopuma_RiccardoBiondi96
Version: 1.0.0.dev1
Summary: Customizable Advanced Tensorflow Objects to Preprocess, Upload, Model and Augment
Home-page: https://github.com/RiccardoBiondi/Catopuma
Download-URL: https://github.com/RiccardoBiondi/Catopuma
Author: Riccardo Biondi
Author-email: Riccardo Biondi <riccardo.biondi7@unibo.it>
License: MIT
Project-URL: Homepage, https://github.com/RiccardoBiondi/Catopuma
Project-URL: Issues, https://github.com/RiccardoBiondi/Catopuma/issues
Platform: any
Classifier: Programming Language :: Python :: 3
Classifier: Operating System :: OS Independent
Requires-Python: >=3.5
